boaHancock/__init__.py
boaHancock/generator.py
boaHancock/templates/.gitignore
boaHancock/templates/__init__.py
boaHancock/templates/setup.py
boaHancock/templates/LICENSE/apache.txt
boaHancock/templates/LICENSE/bsd3-clause.txt
boaHancock/templates/LICENSE/free-Boa.txt
boaHancock/templates/LICENSE/gnu.txt
boaHancock/templates/LICENSE/isc.txt
boaHancock/templates/LICENSE/mit.txt
tests/__init__.py
tests/test_generator.py
boaHancock-1.0.6.dist-info/LICENSE
boaHancock-1.0.6.dist-info/METADATA
boaHancock-1.0.6.dist-info/WHEEL
boaHancock-1.0.6.dist-info/entry_points.txt
boaHancock-1.0.6.dist-info/top_level.txt
boaHancock-1.0.6.dist-info/RECORD
