Metadata-Version: 2.1
Name: boaHancock
Version: 1.0.6
Summary: This is tools to make starter template python for create moduls or library
Home-page: https://github.com/Anammkh/boaHancock
Author: Khoirul Anam
Author-email: khoirulanaam4567@gmail.com
Classifier: Programming Language :: Python :: 3
Classifier: Programming Language :: Python :: 3.9
Classifier: License :: OSI Approved :: MIT License
Classifier: Operating System :: OS Independent
Requires-Python: >=3.6
License-File: LICENSE
Requires-Dist: termcolor
Requires-Dist: pyfiglet
Requires-Dist: colorama
